sklearn_wrap/SKARDRegression.py
sklearn_wrap/SKAdaBoostClassifier.py
sklearn_wrap/SKAdaBoostRegressor.py
sklearn_wrap/SKBaggingClassifier.py
sklearn_wrap/SKBaggingRegressor.py
sklearn_wrap/SKBernoulliNB.py
sklearn_wrap/SKBinarizer.py
sklearn_wrap/SKCountVectorizer.py
sklearn_wrap/SKDecisionTreeClassifier.py
sklearn_wrap/SKDecisionTreeRegressor.py
sklearn_wrap/SKDummyClassifier.py
sklearn_wrap/SKDummyRegressor.py
sklearn_wrap/SKElasticNet.py
sklearn_wrap/SKExtraTreesClassifier.py
sklearn_wrap/SKExtraTreesRegressor.py
sklearn_wrap/SKFastICA.py
sklearn_wrap/SKFeatureAgglomeration.py
sklearn_wrap/SKGaussianNB.py
sklearn_wrap/SKGaussianProcessRegressor.py
sklearn_wrap/SKGaussianRandomProjection.py
sklearn_wrap/SKGenericUnivariateSelect.py
sklearn_wrap/SKGradientBoostingClassifier.py
sklearn_wrap/SKGradientBoostingRegressor.py
sklearn_wrap/SKImputer.py
sklearn_wrap/SKKNeighborsClassifier.py
sklearn_wrap/SKKNeighborsRegressor.py
sklearn_wrap/SKKernelPCA.py
sklearn_wrap/SKKernelRidge.py
sklearn_wrap/SKLars.py
sklearn_wrap/SKLasso.py
sklearn_wrap/SKLassoCV.py
sklearn_wrap/SKLinearDiscriminantAnalysis.py
sklearn_wrap/SKLinearRegression.py
sklearn_wrap/SKLinearSVC.py
sklearn_wrap/SKLinearSVR.py
sklearn_wrap/SKLogisticRegression.py
sklearn_wrap/SKMLPClassifier.py
sklearn_wrap/SKMLPRegressor.py
sklearn_wrap/SKMaxAbsScaler.py
sklearn_wrap/SKMinMaxScaler.py
sklearn_wrap/SKMissingIndicator.py
sklearn_wrap/SKMultinomialNB.py
sklearn_wrap/SKNearestCentroid.py
sklearn_wrap/SKNormalizer.py
sklearn_wrap/SKNystroem.py
sklearn_wrap/SKOneHotEncoder.py
sklearn_wrap/SKOrdinalEncoder.py
sklearn_wrap/SKPCA.py
sklearn_wrap/SKPassiveAggressiveClassifier.py
sklearn_wrap/SKPassiveAggressiveRegressor.py
sklearn_wrap/SKPolynomialFeatures.py
sklearn_wrap/SKQuadraticDiscriminantAnalysis.py
sklearn_wrap/SKQuantileTransformer.py
sklearn_wrap/SKRBFSampler.py
sklearn_wrap/SKRandomForestClassifier.py
sklearn_wrap/SKRandomForestRegressor.py
sklearn_wrap/SKRandomTreesEmbedding.py
sklearn_wrap/SKRidge.py
d3m_sklearn_wrap-2022.2.8.dist-info/METADATA
d3m_sklearn_wrap-2022.2.8.dist-info/WHEEL
d3m_sklearn_wrap-2022.2.8.dist-info/entry_points.txt
d3m_sklearn_wrap-2022.2.8.dist-info/top_level.txt
d3m_sklearn_wrap-2022.2.8.dist-info/RECORD
