Metadata-Version: 2.1
Name: d3m-sklearn-wrap
Version: 2022.2.8
Summary: Primitives created using the Sklearn auto wrapper
Home-page: https://gitlab.com/datadrivendiscovery/sklearn-wrap
Author: TEAM
Author-email: UNKNOWN
License: Apache-2.0
Platform: UNKNOWN
Requires-Dist: d3m
Requires-Dist: scikit-learn (<0.24,>=0.21.3)
